split_nth/__init__.py
split_nth/splitter.py
split_nth-0.1.2.dist-info/METADATA
split_nth-0.1.2.dist-info/WHEEL
split_nth-0.1.2.dist-info/top_level.txt
split_nth-0.1.2.dist-info/RECORD
