Metadata-Version: 2.1
Name: split-nth
Version: 0.1.2
Summary: Split strings at the N-th occurrence of a word
Author: S.Hasini, Deepak Das, Irfan Ahmed
Classifier: Programming Language :: Python :: 3
Classifier: License :: OSI Approved :: MIT License
Classifier: Operating System :: OS Independent
Requires-Python: >=3
